restful_aws_lambda/__init__.py
restful_aws_lambda/decorator.py
restful_aws_lambda/request.py
restful_aws_lambda/route.py
restful_aws_lambda-0.1.2.dist-info/LICENSE
restful_aws_lambda-0.1.2.dist-info/WHEEL
restful_aws_lambda-0.1.2.dist-info/METADATA
restful_aws_lambda-0.1.2.dist-info/RECORD
