Metadata-Version: 2.1
Name: restful-aws-lambda
Version: 0.1.2
Summary: Lightweight framework for building REST API using AWS Lambda + API Gateway
Home-page: https://github.com/Joffreybvn/restful-aws-lambda
License: MIT
Keywords: aws-lambda,serverless,api-gateway,rest-api
Author: Joffrey Bienvenu
Author-email: joffreybvn@gmail.com
Requires-Python: >=3.7.0,<4.0.0
Classifier: License :: OSI Approved :: MIT License
Classifier: Operating System :: OS Independent
Classifier: Programming Language :: Python :: 3
Classifier: Programming Language :: Python :: 3.7
Classifier: Programming Language :: Python :: 3.8
Classifier: Programming Language :: Python :: 3.9
Classifier: Programming Language :: Python :: 3.10
Classifier: Programming Language :: Python :: 3.11
Classifier: Programming Language :: Python :: 3
Project-URL: Documentation, https://restful-aws-lambda.readthedocs.io
Project-URL: Repository, https://github.com/Joffreybvn/restful-aws-lambda
